shipboss_mcp_server.py
shipboss_mcp_server-4.0.12.dist-info/METADATA
shipboss_mcp_server-4.0.12.dist-info/WHEEL
shipboss_mcp_server-4.0.12.dist-info/entry_points.txt
shipboss_mcp_server-4.0.12.dist-info/top_level.txt
shipboss_mcp_server-4.0.12.dist-info/RECORD
