Metadata-Version: 2.4
Name: shipboss-mcp-server
Version: 4.0.12
Summary: ShipBoss MCP server with parcel & freight endpoints
Author-email: ShipBoss <support@shipboss.io>
Keywords: shipping,mcp,shipboss,fastmcp
Classifier: License :: OSI Approved :: MIT License
Classifier: Programming Language :: Python :: 3
Classifier: Programming Language :: Python :: 3 :: Only
Classifier: Programming Language :: Python :: 3.10
Classifier: Programming Language :: Python :: 3.11
Classifier: Programming Language :: Python :: 3.12
Classifier: Operating System :: OS Independent
Requires-Python: >=3.9
Requires-Dist: mcp[cli]==1.2.0
Requires-Dist: httpx>=0.27
Requires-Dist: pydantic>=2.7
Requires-Dist: python-dotenv>=1.0.0
